{
    "kind": "Method",
    "name": "DataView.getFloat32",
    "href": "https://developer.mozilla.org/en-US/docs/Web/JavaScript/Reference/Global_Objects/DataView/getFloat32",
    "description": "The getFloat32() method gets a signed 32-bit float (float) at the specified byte offset from the start of the DataView.",
    "refs": [
        {
            "name": "ECMAScript Language Specification",
            "href": "https://tc39.es/ecma262/multipage/structured-data.html#sec-dataview.prototype.getfloat32",
            "description": "(ECMAScript) # sec-dataview.prototype.getfloat32"
        }
    ]
}
