
{
    "name": "MediaKeySystemAccess",
    "lastModifiedAt": 1629723553683,
    "entries": [
        {
            "name": "__type__",
            "lastModifiedAt": 1629517765000
        },
        {
            "name": "createMediaKeys",
            "lastModifiedAt": 1604976954641
        },
        {
            "name": "getConfiguration",
            "lastModifiedAt": 1604976955147
        },
        {
            "name": "keySystem",
            "lastModifiedAt": 1604976954113
        }
    ]
}
