
{
    "name": "NodeList",
    "lastModifiedAt": 1623484731004,
    "entries": [
        {
            "name": "__type__",
            "lastModifiedAt": 1604977210353
        },
        {
            "name": "entries",
            "lastModifiedAt": 1597193073463
        },
        {
            "name": "forEach",
            "lastModifiedAt": 1604977212414
        },
        {
            "name": "item",
            "lastModifiedAt": 1604977212944
        },
        {
            "name": "keys",
            "lastModifiedAt": 1597193074080
        },
        {
            "name": "length",
            "lastModifiedAt": 1604977210817
        },
        {
            "name": "values",
            "lastModifiedAt": 1597193074302
        }
    ]
}
