
{
    "kind": "Method",
    "name": "Math.imul",
    "href": "https://developer.mozilla.org/en-US/docs/Web/JavaScript/Reference/Global_Objects/Math/imul",
    "description": "The Math.imul() function returns the result of the C-like 32-bit multiplication of the two parameters.",
    "refs": [
        {
            "name": "ECMAScript (ECMA-262)",
            "href": "https://tc39.es/ecma262/#sec-math.imul",
            "description": "The definition of 'Math.imul' in the 'ECMAScript (ECMA-262)' specification."
        }
    ]
}
