
{
    "kind": "Type",
    "name": "SVGFEDropShadowElement",
    "href": "https://developer.mozilla.org/en-US/docs/Web/API/SVGFEDropShadowElement",
    "description": "The SVGFEDropShadowElement interface corresponds to the &lt;feDropShadow&gt; element.",
    "refs": [
        {
            "name": "Filter Effects Module Level 2",
            "href": "https://drafts.fxtf.org/filter-effects/#InterfaceSVGFEDropShadowElement",
            "description": "(Filter Effects 2) # InterfaceSVGFEDropShadowElement"
        }
    ]
}
