
{
    "kind": "Type",
    "name": "HTMLTableRowElement",
    "href": "https://developer.mozilla.org/en-US/docs/Web/API/HTMLTableRowElement",
    "description": "The HTMLTableRowElement interface provides special properties and methods (beyond the HTMLElement interface it also has available to it by inheritance) for manipulating the layout and presentation of rows in an HTML table.",
    "refs": [
        {
            "name": "HTML Standard",
            "href": "https://html.spec.whatwg.org/multipage/tables.html#htmltablerowelement",
            "description": "(HTML) # htmltablerowelement"
        }
    ]
}
