
{
    "name": "HTMLFormElement",
    "lastModifiedAt": 1604976515613,
    "entries": [
        {
            "name": "__type__",
            "lastModifiedAt": 1604976504252
        },
        {
            "name": "acceptCharset",
            "lastModifiedAt": 1604976504772
        },
        {
            "name": "action",
            "lastModifiedAt": 1604976505271
        },
        {
            "name": "elements",
            "lastModifiedAt": 1604976506170
        },
        {
            "name": "encoding",
            "lastModifiedAt": 1596581384943
        },
        {
            "name": "enctype",
            "lastModifiedAt": 1604976507171
        },
        {
            "name": "formdata_event",
            "lastModifiedAt": 1604976513908
        },
        {
            "name": "length",
            "lastModifiedAt": 1604976508211
        },
        {
            "name": "method",
            "lastModifiedAt": 1604976508722
        },
        {
            "name": "name",
            "lastModifiedAt": 1604976509205
        },
        {
            "name": "reportValidity",
            "lastModifiedAt": 1604976511374
        },
        {
            "name": "requestSubmit",
            "lastModifiedAt": 1604976511854
        },
        {
            "name": "reset",
            "lastModifiedAt": 1604976512366
        },
        {
            "name": "reset_event",
            "lastModifiedAt": 1604976515026
        },
        {
            "name": "submit",
            "lastModifiedAt": 1604976513431
        },
        {
            "name": "submit_event",
            "lastModifiedAt": 1604976515613
        },
        {
            "name": "target",
            "lastModifiedAt": 1604976509678
        }
    ]
}
