
{
    "kind": "Type",
    "name": "PeriodicWave",
    "href": "https://developer.mozilla.org/en-US/docs/Web/API/PeriodicWave",
    "description": "The PeriodicWave interface defines a periodic waveform that can be used to shape the output of an OscillatorNode.",
    "refs": [
        {
            "name": "Web Audio API",
            "href": "https://webaudio.github.io/web-audio-api/#periodicwave",
            "description": "The definition of 'PeriodicWave' in the 'Web Audio API' specification."
        }
    ]
}
