
{
    "kind": "Method",
    "name": "Boolean.valueOf",
    "href": "https://developer.mozilla.org/en-US/docs/Web/JavaScript/Reference/Global_Objects/Boolean/valueOf",
    "description": "The valueOf() method returns the primitive value of a Boolean object.",
    "refs": [
        {
            "name": "ECMAScript (ECMA-262)",
            "href": "https://tc39.es/ecma262/#sec-boolean.prototype.valueof",
            "description": "Boolean.prototype.valueOf - ECMAScript (ECMA-262)"
        }
    ]
}
