
{
    "kind": "Type",
    "name": "RTCRtpSynchronizationSource",
    "href": "https://developer.mozilla.org/en-US/docs/Web/API/RTCRtpSynchronizationSource",
    "description": "The RTCRtpSynchronizationSource dictionary of the WebRTC API is used by getSynchronizationSources() to describe a particular synchronization source (SSRC).",
    "refs": [
        {
            "name": "WebRTC 1.0: Real-time Communication Between Browsers",
            "href": "https://w3c.github.io/webrtc-pc/#dom-rtcrtpsynchronizationsource",
            "description": "The definition of 'RTCRtpSynchronizationSource' in the 'WebRTC 1.0: Real-time Communication Between Browsers' specification."
        }
    ]
}
