
{
    "kind": "Method",
    "name": "URLSearchParams.sort",
    "href": "https://developer.mozilla.org/en-US/docs/Web/API/URLSearchParams/sort",
    "description": "The URLSearchParams.sort() method sorts all key/value pairs contained in this object in place and returns undefined. The sort order is according to unicode code points of the keys. This method uses a stable sorting algorithm (i.e. the relative order between key/value pairs with equal keys will be preserved).",
    "refs": [
        {
            "name": "URL",
            "href": "https://url.spec.whatwg.org/#dom-urlsearchparams-sort",
            "description": "The definition of 'sort()' in URL."
        }
    ]
}
