
{
    "kind": "Property",
    "name": "GlobalEventHandlers.onkeydown",
    "href": "https://developer.mozilla.org/en-US/docs/Web/API/GlobalEventHandlers/onkeydown",
    "description": "The onkeydown property of the GlobalEventHandlers mixin is an EventHandler that processes keydown events.",
    "refs": [
        {
            "name": "HTML Living Standard",
            "href": "https://html.spec.whatwg.org/multipage/webappapis.html#handler-onkeydown",
            "description": "onkeydown - HTML Living Standard"
        }
    ]
}
