{
    "kind": "Type",
    "name": "IDBKeyRange",
    "href": "https://developer.mozilla.org/en-US/docs/Web/API/IDBKeyRange",
    "description": "The IDBKeyRange interface of the IndexedDB API represents a continuous interval over some data type that is used for keys. Records can be retrieved from IDBObjectStore and IDBIndex objects using keys or a range of keys. You can limit the range using lower and upper bounds. For example, you can iterate over all values of a key in the value range A&ndash;Z.",
    "refs": [
        {
            "name": "Indexed Database API 3.0",
            "href": "https://w3c.github.io/IndexedDB/#keyrange",
            "description": "# keyrange"
        }
    ]
}
