
{
    "kind": "Type",
    "name": "SVGRadialGradientElement",
    "href": "https://developer.mozilla.org/en-US/docs/Web/API/SVGRadialGradientElement",
    "description": "The SVGRadialGradientElement interface corresponds to the RadialGradient element.",
    "refs": [
        {
            "name": "Scalable Vector Graphics (SVG) 2",
            "href": "https://svgwg.org/svg2-draft/pservers.html#InterfaceSVGRadialGradientElement",
            "description": "The definition of 'SVGRadialGradientElement' in the 'Scalable Vector Graphics (SVG) 2' specification."
        },
        {
            "name": "Scalable Vector Graphics (SVG) 1.1 (Second Edition)",
            "href": "https://www.w3.org/TR/SVG11/pservers.html#InterfaceSVGRadialGradientElement",
            "description": "The definition of 'SVGRadialGradientElement' in the 'Scalable Vector Graphics (SVG) 1.1 (Second Edition)' specification."
        }
    ]
}
