
{
    "kind": "Method",
    "name": "Window.setImmediate",
    "href": "https://developer.mozilla.org/en-US/docs/Web/API/Window/setImmediate",
    "description": "This method is used to break up long running operations and run a callback function immediately after the browser has completed other operations such as events and display updates.",
    "refs": [
        {
            "name": "Efficient Script Yielding",
            "href": "https://w3c.github.io/setImmediate/#si-setImmediate",
            "description": "The definition of 'setImmediate' in Efficient Script Yielding."
        }
    ]
}
