{
    "name": "PannerNode",
    "lastModifiedAt": 1629723658167,
    "entries": [
        {
            "name": "PannerNode",
            "lastModifiedAt": 1604977267875
        },
        {
            "name": "__type__",
            "lastModifiedAt": 1629517779000
        },
        {
            "name": "coneInnerAngle",
            "lastModifiedAt": 1604977268991
        },
        {
            "name": "coneOuterAngle",
            "lastModifiedAt": 1604977269523
        },
        {
            "name": "coneOuterGain",
            "lastModifiedAt": 1604977270556
        },
        {
            "name": "distanceModel",
            "lastModifiedAt": 1604977271161
        },
        {
            "name": "maxDistance",
            "lastModifiedAt": 1604977271650
        },
        {
            "name": "orientationX",
            "lastModifiedAt": 1604977272211
        },
        {
            "name": "orientationY",
            "lastModifiedAt": 1604977272729
        },
        {
            "name": "orientationZ",
            "lastModifiedAt": 1604977273424
        },
        {
            "name": "panningModel",
            "lastModifiedAt": 1604977274455
        },
        {
            "name": "positionX",
            "lastModifiedAt": 1604977275458
        },
        {
            "name": "positionY",
            "lastModifiedAt": 1604977276477
        },
        {
            "name": "positionZ",
            "lastModifiedAt": 1604977277117
        },
        {
            "name": "refDistance",
            "lastModifiedAt": 1604977278177
        },
        {
            "name": "rolloffFactor",
            "lastModifiedAt": 1604977278714
        },
        {
            "name": "setOrientation",
            "lastModifiedAt": 1604977279309
        },
        {
            "name": "setPosition",
            "lastModifiedAt": 1604977279827
        },
        {
            "name": "setVelocity",
            "lastModifiedAt": 1600307054505
        }
    ]
}
