
{
    "kind": "Method",
    "name": "Symbol.keyFor",
    "href": "https://developer.mozilla.org/en-US/docs/Web/JavaScript/Reference/Global_Objects/Symbol/keyFor",
    "description": "The Symbol.keyFor(sym) method retrieves a shared symbol key from the global symbol registry for the given symbol.",
    "refs": [
        {
            "name": "ECMAScript Language Specification",
            "href": "https://tc39.es/ecma262/multipage/fundamental-objects.html#sec-symbol.keyfor",
            "description": "(ECMAScript) # sec-symbol.keyfor"
        }
    ]
}
