{
    "kind": "Type",
    "name": "HTMLMeterElement",
    "href": "https://developer.mozilla.org/en-US/docs/Web/API/HTMLMeterElement",
    "description": "The HTML &lt;meter&gt; elements expose the HTMLMeterElement interface, which provides special properties and methods (beyond the HTMLElement object interface they also have available to them by inheritance) for manipulating the layout and presentation of &lt;meter&gt; elements.",
    "refs": [
        {
            "name": "HTML Standard",
            "href": "https://html.spec.whatwg.org/multipage/form-elements.html#htmlmeterelement",
            "description": "# htmlmeterelement"
        }
    ]
}
